osdu_perf/__init__.py
osdu_perf/cli/__init__.py
osdu_perf/cli/arg_parser.py
osdu_perf/cli/command_base.py
osdu_perf/cli/command_factory.py
osdu_perf/cli/command_invoker.py
osdu_perf/cli/main.py
osdu_perf/cli/commands/__init__.py
osdu_perf/cli/commands/init_command.py
osdu_perf/cli/commands/run_azure_command.py
osdu_perf/cli/commands/run_local_command.py
osdu_perf/cli/commands/version_command.py
osdu_perf/locust_integration/__init__.py
osdu_perf/locust_integration/user_base.py
osdu_perf/operations/__init__.py
osdu_perf/operations/auth.py
osdu_perf/operations/base_service.py
osdu_perf/operations/entitlement.py
osdu_perf/operations/input_handler.py
osdu_perf/operations/service_orchestrator.py
osdu_perf/operations/azure_test_operation/__init__.py
osdu_perf/operations/azure_test_operation/azure_test_runner.py
osdu_perf/operations/azure_test_operation/config.py
osdu_perf/operations/azure_test_operation/entitlement_manager.py
osdu_perf/operations/azure_test_operation/file_manager.py
osdu_perf/operations/azure_test_operation/resource_manager.py
osdu_perf/operations/azure_test_operation/test_executor.py
osdu_perf/operations/init_operation/__init__.py
osdu_perf/operations/init_operation/init_runner.py
osdu_perf/operations/local_test_operation/__init__.py
osdu_perf/operations/local_test_operation/local_test_runner.py
osdu_perf/utils/__init__.py
osdu_perf/utils/environment.py
osdu_perf/utils/logger.py
osdu_perf-1.0.30.dist-info/licenses/LICENSE
osdu_perf-1.0.30.dist-info/METADATA
osdu_perf-1.0.30.dist-info/WHEEL
osdu_perf-1.0.30.dist-info/entry_points.txt
osdu_perf-1.0.30.dist-info/top_level.txt
osdu_perf-1.0.30.dist-info/RECORD
